MANIFEST.in
README.rst
setup.py
imgurt/__init__.py
imgurt/__main__.py
imgurt/imgurt.ini
imgurt/imgurt.py
imgurt/tune.py
imgurt.egg-info/PKG-INFO
imgurt.egg-info/SOURCES.txt
imgurt.egg-info/dependency_links.txt
imgurt.egg-info/entry_points.txt
imgurt.egg-info/requires.txt
imgurt.egg-info/top_level.txt