Metadata-Version: 1.1
Name: imgurt
Version: 1.4.1
Summary: uses math to select wallpapers from Reddit
Home-page: https://github.com/evidlo/imgurt
Author: Evan Widloski
Author-email: evan@evanw.org
License: MIT
Keywords: imgur reddit wallpaper changer
Platform: UNKNOWN
Classifier: Programming Language :: Python :: 2
Classifier: Programming Language :: Python :: 3
